[
  {
    "id": "llama3-8b",
    "name": "Llama 3 8B",
    "ollamaTag": "llama3:8b",
    "sizeGb": 4.7,
    "capability": "generate",
    "license": "Meta Llama 3 Community License (open-weight)",
    "tier": "recommended",
    "useCases": ["general", "code"],
    "hardware": { "ramGb": 8, "vramGb": 6 },
    "description": "Meta's flagship open-weight model. Strong general reasoning and code generation."
  },
  {
    "id": "llama3-70b",
    "name": "Llama 3 70B",
    "ollamaTag": "llama3:70b",
    "sizeGb": 40,
    "capability": "generate",
    "license": "Meta Llama 3 Community License (open-weight)",
    "tier": "recommended",
    "useCases": ["general", "code"],
    "hardware": { "ramGb": 64, "vramGb": 48 },
    "description": "Full-size Llama 3. Top-tier reasoning for air-gapped deployments."
  },
  {
    "id": "mistral-7b",
    "name": "Mistral 7B",
    "ollamaTag": "mistral:7b",
    "sizeGb": 4.1,
    "capability": "generate",
    "license": "Apache 2.0",
    "tier": "recommended",
    "useCases": ["general", "multilingual"],
    "hardware": { "ramGb": 8, "vramGb": 6 },
    "description": "Efficient European-built model with strong multilingual support."
  },
  {
    "id": "phi3-mini",
    "name": "Phi-3 Mini",
    "ollamaTag": "phi3:mini",
    "sizeGb": 2.3,
    "capability": "generate",
    "license": "MIT",
    "tier": "lightweight",
    "useCases": ["general"],
    "hardware": { "ramGb": 4, "vramGb": 3 },
    "description": "Microsoft's compact model. Excellent quality-to-size ratio for constrained hardware."
  },
  {
    "id": "phi3-medium",
    "name": "Phi-3 Medium",
    "ollamaTag": "phi3:medium",
    "sizeGb": 7.9,
    "capability": "generate",
    "license": "MIT",
    "tier": "recommended",
    "useCases": ["general", "code"],
    "hardware": { "ramGb": 16, "vramGb": 10 },
    "description": "Mid-size Phi-3 with stronger reasoning than Mini."
  },
  {
    "id": "codellama-7b",
    "name": "CodeLlama 7B",
    "ollamaTag": "codellama:7b",
    "sizeGb": 3.8,
    "capability": "generate",
    "license": "Meta Llama 2 Community License (open-weight)",
    "tier": "specialized",
    "useCases": ["code"],
    "hardware": { "ramGb": 8, "vramGb": 6 },
    "description": "Code-specialized Llama variant. Optimized for code completion and generation."
  },
  {
    "id": "codellama-34b",
    "name": "CodeLlama 34B",
    "ollamaTag": "codellama:34b",
    "sizeGb": 19,
    "capability": "generate",
    "license": "Meta Llama 2 Community License (open-weight)",
    "tier": "specialized",
    "useCases": ["code"],
    "hardware": { "ramGb": 32, "vramGb": 24 },
    "description": "Larger CodeLlama for complex code tasks and infilling."
  },
  {
    "id": "nomic-embed-text",
    "name": "Nomic Embed Text",
    "ollamaTag": "nomic-embed-text",
    "sizeGb": 0.27,
    "capability": "embed",
    "license": "Apache 2.0",
    "tier": "recommended",
    "useCases": ["embedding"],
    "hardware": { "ramGb": 2, "vramGb": 1 },
    "description": "High-quality text embeddings. Recommended default for RAG pipelines."
  },
  {
    "id": "all-minilm",
    "name": "All-MiniLM-L6",
    "ollamaTag": "all-minilm",
    "sizeGb": 0.07,
    "capability": "embed",
    "license": "Apache 2.0",
    "tier": "lightweight",
    "useCases": ["embedding"],
    "hardware": { "ramGb": 1, "vramGb": 0 },
    "description": "Ultra-light embedding model. Runs on CPU-only hardware."
  },
  {
    "id": "biomistral-7b",
    "name": "BioMistral 7B",
    "ollamaTag": "biomistral",
    "sizeGb": 4.1,
    "capability": "generate",
    "license": "Apache 2.0",
    "tier": "specialized",
    "useCases": ["medical"],
    "hardware": { "ramGb": 8, "vramGb": 6 },
    "description": "Medical domain model built on Mistral. For healthcare document processing."
  },
  {
    "id": "mistral-openorca",
    "name": "Mistral OpenOrca",
    "ollamaTag": "mistral-openorca",
    "sizeGb": 4.1,
    "capability": "generate",
    "license": "Apache 2.0",
    "tier": "recommended",
    "useCases": ["general", "multilingual"],
    "hardware": { "ramGb": 8, "vramGb": 6 },
    "description": "Instruction-tuned Mistral with broad task coverage."
  },
  {
    "id": "nous-hermes2",
    "name": "Nous Hermes 2 Mistral",
    "ollamaTag": "nous-hermes2",
    "sizeGb": 4.1,
    "capability": "generate",
    "license": "Apache 2.0",
    "tier": "recommended",
    "useCases": ["general", "legal"],
    "hardware": { "ramGb": 8, "vramGb": 6 },
    "description": "Fine-tuned for structured reasoning. Good for legal and analytical tasks."
  }
]
